zzzerocard/__init__.py
zzzerocard/client.py
zzzerocard/src/assets/font/zzz_font.otf
zzzerocard/src/components/api.py
zzzerocard/src/components/card.py
zzzerocard/src/components/main.py
zzzerocard/src/generator/style_one.py
zzzerocard/src/model/card.py
zzzerocard/src/model/character.py
zzzerocard/src/model/wiki.py
zzzerocard/src/tools/cache.py
zzzerocard/src/tools/git.py
zzzerocard/src/tools/http.py
zzzerocard/src/tools/json_data.py
zzzerocard/src/tools/pill/__init__.py
zzzerocard/src/tools/pill/color.py
zzzerocard/src/tools/pill/color_control.py
zzzerocard/src/tools/pill/gradient_v2.py
zzzerocard/src/tools/pill/grandient_v1.py
zzzerocard/src/tools/pill/image_control.py
zzzerocard/src/tools/pill/text_control.py
zzzerocard/src/tools/settings.py
zzzerocard-0.1.2.dist-info/METADATA
zzzerocard-0.1.2.dist-info/WHEEL
zzzerocard-0.1.2.dist-info/RECORD
