Metadata-Version: 2.1
Name: zzzerocard
Version: 0.1.2
Summary: Module for creating cards with characters from the game Zenless zone zero!
Home-page: https://github.com/DEViantUA/ZZZeroCard
License: MIT
Keywords: api,generator,card,hoyolab,zenless zone zero,zzzero,zzzerocard,starrailcard
Author: DeviantUa
Author-email: deviantapi@gmail.com
Requires-Python: >=3.9
Classifier: License :: OSI Approved :: MIT License
Classifier: Programming Language :: Python :: 3
Classifier: Programming Language :: Python :: 3.9
Classifier: Programming Language :: Python :: 3.10
Classifier: Programming Language :: Python :: 3.11
Requires-Dist: Pillow
Requires-Dist: aiofiles
Requires-Dist: aiohttp
Requires-Dist: beautifulsoup4
Requires-Dist: cachetools
Requires-Dist: more-itertools
Requires-Dist: numpy
Requires-Dist: pydantic
Project-URL: Repository, https://github.com/DEViantUA/ZZZeroCard
